Nexgram/__init__.py
Nexgram/api.py
Nexgram/client.py
Nexgram/filters.py
Nexgram/idle.py
Nexgram/import_all.py
Nexgram/enums/__init__.py
Nexgram/errors/BadRequest.py
Nexgram/errors/InvalidObject.py
Nexgram/errors/PollingAlreadyStartedError.py
Nexgram/errors/__init__.py
Nexgram/methods/__init__.py
Nexgram/methods/chats/__init__.py
Nexgram/methods/chats/get_chat_member.py
Nexgram/methods/decorators/__init__.py
Nexgram/methods/decorators/on.py
Nexgram/methods/decorators/on_callback_query.py
Nexgram/methods/decorators/on_disconnect.py
Nexgram/methods/decorators/on_inline_query.py
Nexgram/methods/decorators/on_message.py
Nexgram/methods/messages/__init__.py
Nexgram/methods/messages/copy_messages.py
Nexgram/methods/messages/forward_messages.py
Nexgram/methods/messages/send_message.py
Nexgram/methods/utilities/__init__.py
Nexgram/methods/utilities/call.py
Nexgram/methods/utilities/create_object.py
Nexgram/methods/utilities/dispatch_update.py
Nexgram/methods/utilities/start.py
Nexgram/methods/utilities/start_polling.py
Nexgram/methods/utilities/stop.py
Nexgram/methods/utilities/webhook.py
Nexgram/types/__init__.py
Nexgram/types/chats/__init__.py
Nexgram/types/chats/chat.py
Nexgram/types/chats/user.py
Nexgram/types/keyboards/__init__.py
Nexgram/types/keyboards/inline_keyboard_button.py
Nexgram/types/keyboards/inline_keyboard_markup.py
Nexgram/types/messages_and_media/__init__.py
Nexgram/types/messages_and_media/message.py
Nexgram/types/updates/CallbackQuery.py
Nexgram/types/updates/ChatJoinRequest.py
Nexgram/types/updates/InlineQuery.py
Nexgram/types/updates/__init__.py
nexgram_py-0.0.27.dist-info/METADATA
nexgram_py-0.0.27.dist-info/WHEEL
nexgram_py-0.0.27.dist-info/top_level.txt
nexgram_py-0.0.27.dist-info/RECORD
