Metadata-Version: 2.4
Name: Nexgram.py
Version: 0.0.27
Summary: just a try
Home-page: https://github.com/Otazuki004/Nexgram.py
Author: Otazuki
Author-email: otazuki004@gmail.com
Classifier: Programming Language :: Python :: 3
Classifier: License :: OSI Approved :: MIT License
Classifier: Operating System :: OS Independent
Requires-Python: >=3.12
Requires-Dist: aiofiles
Requires-Dist: aiohttp
Requires-Dist: httpx
Dynamic: author
Dynamic: author-email
Dynamic: classifier
Dynamic: description
Dynamic: description-content-type
Dynamic: home-page
Dynamic: requires-dist
Dynamic: requires-python
Dynamic: summary
